vec3d/graph/__init__.py
vec3d/graph/vector3d_graphics.py
vec3d/math/__init__.py
vec3d/math/vector3d_math.py
vec3d-0.2.4.dist-info/LICENSE
vec3d-0.2.4.dist-info/METADATA
vec3d-0.2.4.dist-info/WHEEL
vec3d-0.2.4.dist-info/RECORD
