Metadata-Version: 2.1
Name: vec3d
Version: 0.2.4
Summary: Maths and graph functions for vectors in the 3D space
Home-page: https://github.com/sergiofgonzalez/vec3d
License: MIT
Author: Sergio F. Gonzalez
Author-email: sergio.f.gonzalez@gmail.com
Requires-Python: >=3.10,<4.0
Classifier: License :: OSI Approved :: MIT License
Classifier: Programming Language :: Python :: 3
Classifier: Programming Language :: Python :: 3.10
Classifier: Programming Language :: Python :: 3.11
Classifier: Programming Language :: Python :: 3.12
Requires-Dist: matplotlib (>=3.8.2,<4.0.0)
Requires-Dist: numpy (>=1.26.3,<2.0.0)
Project-URL: Repository, https://github.com/sergiofgonzalez/vec3d
